detr/__init__.py
detr/datasets/__init__.py
detr/datasets/coco.py
detr/datasets/coco_eval.py
detr/datasets/coco_panoptic.py
detr/datasets/panoptic_eval.py
detr/datasets/transforms.py
detr/models/__init__.py
detr/models/backbone.py
detr/models/detr.py
detr/models/matcher.py
detr/models/position_encoding.py
detr/models/segmentation.py
detr/models/transformer.py
detr/util/__init__.py
detr/util/box_ops.py
detr/util/misc.py
detr/util/plot_utils.py
python_detr-0.1.7.dist-info/LICENSE
python_detr-0.1.7.dist-info/METADATA
python_detr-0.1.7.dist-info/WHEEL
python_detr-0.1.7.dist-info/dependency_links.txt
python_detr-0.1.7.dist-info/top_level.txt
python_detr-0.1.7.dist-info/RECORD
