Metadata-Version: 2.1
Name: python-detr
Version: 0.1.7
Home-page: https://github.com/facebookresearch/detr
Author: facebookresearch
Classifier: Programming Language :: Python :: 3
Classifier: Programming Language :: Python :: 3.8
Requires-Python: >=3.8
License-File: LICENSE
Requires-Dist: cython
Requires-Dist: pycocotools
Requires-Dist: submitit
Requires-Dist: torch >=1.5.0
Requires-Dist: torchvision >=0.6.0
Requires-Dist: scipy
Requires-Dist: onnx
Requires-Dist: onnxruntime
